{
 "scenario_id": "d68b47b902c21a8e",
 "seed": 73,
 "controller": "enhanced_wheel",
 "selected_instruction": "merge left",
 "selected_onset_manual": 11,
 "selected_instruction_index": 0,
 "collect_start_index": 0,
 "takeover_start_index": 11,
 "frames": [
  0,
  1,
  2,
  3,
  4,
  5,
  6,
  7,
  8,
  9,
  10,
  11,
  12,
  13,
  14,
  15,
  16,
  17,
  18,
  19,
  20,
  21,
  22,
  23,
  24,
  25,
  26,
  27,
  28,
  29,
  30,
  31,
  32,
  33,
  34,
  35,
  36,
  37,
  38,
  39,
  40,
  41,
  42,
  43,
  44,
  45,
  46,
  47,
  48,
  49,
  50,
  51,
  52,
  53,
  54,
  55,
  56,
  57,
  58,
  59,
  60,
  61,
  62,
  63,
  64,
  65,
  66,
  67,
  68,
  69,
  70,
  71,
  72,
  73,
  74,
  75,
  76,
  77,
  78,
  79,
  80,
  81,
  82,
  83,
  84,
  85,
  86,
  87,
  88,
  89,
  90,
  91,
  92,
  93,
  94,
  95,
  96,
  97,
  98,
  99,
  100,
  101,
  102,
  103,
  104,
  105,
  106,
  107,
  108,
  109,
  110,
  111,
  112,
  113,
  114,
  115,
  116,
  117,
  118,
  119,
  120,
  121,
  122,
  123,
  124,
  125,
  126,
  127,
  128,
  129,
  130,
  131,
  132,
  133,
  134,
  135,
  136,
  137,
  138,
  139,
  140,
  141,
  142,
  143,
  144,
  145,
  146,
  147,
  148,
  149,
  150,
  151,
  152,
  153,
  154,
  155,
  156,
  157,
  158,
  159,
  160,
  161,
  162,
  163,
  164,
  165,
  166,
  167,
  168,
  169,
  170,
  171,
  172,
  173,
  174,
  175,
  176,
  177,
  178,
  179,
  180,
  181,
  182,
  183,
  184,
  185,
  186,
  187,
  188,
  189,
  190,
  191,
  192,
  193,
  194,
  195,
  196,
  197,
  198,
  199,
  200,
  201,
  202,
  203,
  204,
  205,
  206,
  207
 ],
 "timestamps": [
  0.0,
  1.0,
  2.0,
  3.0,
  4.0,
  5.0,
  6.0,
  7.0,
  8.0,
  9.0,
  10.0,
  11.0,
  12.0,
  13.0,
  14.0,
  15.0,
  16.0,
  17.0,
  18.0,
  19.0,
  20.0,
  21.0,
  22.0,
  23.0,
  24.0,
  25.0,
  26.0,
  27.0,
  28.0,
  29.0,
  30.0,
  31.0,
  32.0,
  33.0,
  34.0,
  35.0,
  36.0,
  37.0,
  38.0,
  39.0,
  40.0,
  41.0,
  42.0,
  43.0,
  44.0,
  45.0,
  46.0,
  47.0,
  48.0,
  49.0,
  50.0,
  51.0,
  52.0,
  53.0,
  54.0,
  55.0,
  56.0,
  57.0,
  58.0,
  59.0,
  60.0,
  61.0,
  62.0,
  63.0,
  64.0,
  65.0,
  66.0,
  67.0,
  68.0,
  69.0,
  70.0,
  71.0,
  72.0,
  73.0,
  74.0,
  75.0,
  76.0,
  77.0,
  78.0,
  79.0,
  80.0,
  81.0,
  82.0,
  83.0,
  84.0,
  85.0,
  86.0,
  87.0,
  88.0,
  89.0,
  90.0,
  91.0,
  92.0,
  93.0,
  94.0,
  95.0,
  96.0,
  97.0,
  98.0,
  99.0,
  100.0,
  101.0,
  102.0,
  103.0,
  104.0,
  105.0,
  106.0,
  107.0,
  108.0,
  109.0,
  110.0,
  111.0,
  112.0,
  113.0,
  114.0,
  115.0,
  116.0,
  117.0,
  118.0,
  119.0,
  120.0,
  121.0,
  122.0,
  123.0,
  124.0,
  125.0,
  126.0,
  127.0,
  128.0,
  129.0,
  130.0,
  131.0,
  132.0,
  133.0,
  134.0,
  135.0,
  136.0,
  137.0,
  138.0,
  139.0,
  140.0,
  141.0,
  142.0,
  143.0,
  144.0,
  145.0,
  146.0,
  147.0,
  148.0,
  149.0,
  150.0,
  151.0,
  152.0,
  153.0,
  154.0,
  155.0,
  156.0,
  157.0,
  158.0,
  159.0,
  160.0,
  161.0,
  162.0,
  163.0,
  164.0,
  165.0,
  166.0,
  167.0,
  168.0,
  169.0,
  170.0,
  171.0,
  172.0,
  173.0,
  174.0,
  175.0,
  176.0,
  177.0,
  178.0,
  179.0,
  180.0,
  181.0,
  182.0,
  183.0,
  184.0,
  185.0,
  186.0,
  187.0,
  188.0,
  189.0,
  190.0,
  191.0,
  192.0,
  193.0,
  194.0,
  195.0,
  196.0,
  197.0,
  198.0,
  199.0,
  200.0,
  201.0,
  202.0,
  203.0,
  204.0,
  205.0,
  206.0,
  207.0
 ],
 "is_manual": [
  false,
  false,
  false,
  false,
  false,
  false,
  false,
  false,
  false,
  false,
  false,
  true,
  true,
  true,
  true,
  true,
  true,
  true,
  true,
  true,
  true,
  true,
  true,
  true,
  true,
  true,
  true,
  true,
  true,
  true,
  true,
  true,
  true,
  true,
  true,
  true,
  true,
  true,
  true,
  true,
  true,
  true,
  true,
  true,
  true,
  true,
  true,
  true,
  true,
  true,
  true,
  true,
  true,
  true,
  true,
  true,
  true,
  true,
  true,
  true,
  true,
  true,
  true,
  true,
  true,
  true,
  true,
  true,
  true,
  true,
  true,
  true,
  true,
  true,
  true,
  true,
  true,
  true,
  true,
  true,
  true,
  true,
  true,
  true,
  true,
  true,
  true,
  true,
  true,
  true,
  true,
  true,
  true,
  true,
  true,
  true,
  true,
  true,
  true,
  true,
  true,
  true,
  true,
  true,
  true,
  true,
  true,
  true,
  true,
  true,
  true,
  true,
  true,
  true,
  true,
  true,
  true,
  true,
  true,
  true,
  true,
  true,
  true,
  true,
  true,
  true,
  true,
  true,
  true,
  true,
  true,
  true,
  true,
  true,
  true,
  true,
  true,
  true,
  true,
  true,
  true,
  true,
  true,
  true,
  true,
  true,
  true,
  true,
  true,
  true,
  true,
  true,
  true,
  true,
  true,
  true,
  true,
  true,
  true,
  true,
  true,
  true,
  true,
  true,
  true,
  true,
  true,
  true,
  true,
  true,
  true,
  true,
  true,
  true,
  true,
  true,
  true,
  true,
  true,
  true,
  true,
  true,
  true,
  true,
  true,
  true,
  true,
  true,
  true,
  true,
  true,
  true,
  true,
  true,
  true,
  true,
  true,
  true,
  true,
  true,
  true,
  true,
  true,
  true,
  true,
  true,
  true,
  true
 ],
 "positions": [
  [
   1.465142846107483,
   0.015193457715213299
  ],
  [
   3.296438694000244,
   0.045873068273067474
  ],
  [
   5.114359378814697,
   0.0763472244143486
  ],
  [
   6.922460079193115,
   0.1067366749048233
  ],
  [
   8.719120025634766,
   0.13671875
  ],
  [
   10.504603385925293,
   0.16729649901390076
  ],
  [
   12.277591705322266,
   0.19765184819698334
  ],
  [
   14.040283203125,
   0.22727812826633453
  ],
  [
   15.791531562805176,
   0.2554365396499634
  ],
  [
   17.53274154663086,
   0.28241753578186035
  ],
  [
   19.26228141784668,
   0.3079516887664795
  ],
  [
   20.989830017089844,
   0.3110017478466034
  ],
  [
   22.710399627685547,
   0.29789599776268005
  ],
  [
   24.423723220825195,
   0.26681268215179443
  ],
  [
   26.1296329498291,
   0.21694105863571167
  ],
  [
   27.827970504760742,
   0.14816755056381226
  ],
  [
   29.518583297729492,
   0.06066371873021126
  ],
  [
   31.20132827758789,
   -0.045315057039260864
  ],
  [
   32.87606430053711,
   -0.16951802372932434
  ],
  [
   34.542659759521484,
   -0.3117070198059082
  ],
  [
   36.20097732543945,
   -0.4716534912586212
  ],
  [
   37.850887298583984,
   -0.649133563041687
  ],
  [
   39.49227523803711,
   -0.8439167141914368
  ],
  [
   41.12501525878906,
   -1.0557730197906494
  ],
  [
   42.74898910522461,
   -1.2844781875610352
  ],
  [
   44.36408615112305,
   -1.529809594154358
  ],
  [
   45.97019958496094,
   -1.7915444374084473
  ],
  [
   47.56721496582031,
   -2.0694596767425537
  ],
  [
   49.15503692626953,
   -2.3633344173431396
  ],
  [
   50.73356628417969,
   -2.672950267791748
  ],
  [
   52.30270767211914,
   -2.998091459274292
  ],
  [
   53.862369537353516,
   -3.338543176651001
  ],
  [
   55.4124641418457,
   -3.694091558456421
  ],
  [
   56.95290756225586,
   -4.064523220062256
  ],
  [
   58.483612060546875,
   -4.44962739944458
  ],
  [
   60.0045051574707,
   -4.849194049835205
  ],
  [
   61.515506744384766,
   -5.263014793395996
  ],
  [
   63.016544342041016,
   -5.690882205963135
  ],
  [
   64.5075454711914,
   -6.13259220123291
  ],
  [
   65.98844909667969,
   -6.587941646575928
  ],
  [
   67.45917510986328,
   -7.056728363037109
  ],
  [
   68.91968536376953,
   -7.538751125335693
  ],
  [
   70.36991119384766,
   -8.03381061553955
  ],
  [
   71.80978393554688,
   -8.54171085357666
  ],
  [
   73.2392578125,
   -9.062254905700684
  ],
  [
   74.65828704833984,
   -9.595248222351074
  ],
  [
   76.06681823730469,
   -10.140499114990234
  ],
  [
   77.46479797363281,
   -10.697815895080566
  ],
  [
   78.85218811035156,
   -11.267008781433105
  ],
  [
   80.22895050048828,
   -11.84788990020752
  ],
  [
   81.59503173828125,
   -12.440272331237793
  ],
  [
   82.95040893554688,
   -13.043973922729492
  ],
  [
   84.2950439453125,
   -13.658808708190918
  ],
  [
   85.62889862060547,
   -14.28459644317627
  ],
  [
   86.95194244384766,
   -14.921154975891113
  ],
  [
   88.26416015625,
   -15.568307876586914
  ],
  [
   89.56550598144531,
   -16.22587776184082
  ],
  [
   90.85596466064453,
   -16.893686294555664
  ],
  [
   92.13551330566406,
   -17.571563720703125
  ],
  [
   93.40411376953125,
   -18.259336471557617
  ],
  [
   94.66177368164062,
   -18.956832885742188
  ],
  [
   95.908447265625,
   -19.663883209228516
  ],
  [
   97.1441421508789,
   -20.380319595336914
  ],
  [
   98.36883544921875,
   -21.105976104736328
  ],
  [
   99.58250427246094,
   -21.840688705444336
  ],
  [
   100.78515625,
   -22.58429718017578
  ],
  [
   101.97676849365234,
   -23.33663558959961
  ],
  [
   103.15734100341797,
   -24.097545623779297
  ],
  [
   104.32685089111328,
   -24.866867065429688
  ],
  [
   105.4853286743164,
   -25.644445419311523
  ],
  [
   106.63275146484375,
   -26.43012237548828
  ],
  [
   107.76911163330078,
   -27.22374725341797
  ],
  [
   108.8944091796875,
   -28.025163650512695
  ],
  [
   110.0086441040039,
   -28.8342227935791
  ],
  [
   111.11181640625,
   -29.650772094726562
  ],
  [
   112.20394897460938,
   -30.47466468811035
  ],
  [
   113.2850341796875,
   -31.305757522583008
  ],
  [
   114.3550796508789,
   -32.143898010253906
  ],
  [
   115.41409301757812,
   -32.98894500732422
  ],
  [
   116.46208190917969,
   -33.840763092041016
  ],
  [
   117.49905395507812,
   -34.69919967651367
  ],
  [
   118.52503204345703,
   -35.56412124633789
  ],
  [
   119.54000854492188,
   -36.435394287109375
  ],
  [
   120.54400634765625,
   -37.3128776550293
  ],
  [
   121.53704071044922,
   -38.19643783569336
  ],
  [
   122.51913452148438,
   -39.0859375
  ],
  [
   123.49029541015625,
   -39.98124313354492
  ],
  [
   124.4505386352539,
   -40.882225036621094
  ],
  [
   125.39988708496094,
   -41.788753509521484
  ],
  [
   126.33834838867188,
   -42.70070266723633
  ],
  [
   127.2659683227539,
   -43.617942810058594
  ],
  [
   128.18275451660156,
   -44.54034423828125
  ],
  [
   129.08871459960938,
   -45.46778869628906
  ],
  [
   129.98388671875,
   -46.400150299072266
  ],
  [
   130.8682861328125,
   -47.337303161621094
  ],
  [
   131.741943359375,
   -48.279136657714844
  ],
  [
   132.6049041748047,
   -49.225521087646484
  ],
  [
   133.45718383789062,
   -50.17634582519531
  ],
  [
   134.2987823486328,
   -51.13148498535156
  ],
  [
   135.12973022460938,
   -52.0908317565918
  ],
  [
   135.9500732421875,
   -53.05426788330078
  ],
  [
   136.75982666015625,
   -54.02168655395508
  ],
  [
   137.5590362548828,
   -54.99296569824219
  ],
  [
   138.34774780273438,
   -55.96800231933594
  ],
  [
   139.12596130371094,
   -56.94668960571289
  ],
  [
   139.89370727539062,
   -57.928916931152344
  ],
  [
   140.65103149414062,
   -58.91456985473633
  ],
  [
   141.39796447753906,
   -59.9035530090332
  ],
  [
   142.134521484375,
   -60.895751953125
  ],
  [
   142.8607635498047,
   -61.891075134277344
  ],
  [
   143.5767059326172,
   -62.8894157409668
  ],
  [
   144.28240966796875,
   -63.890663146972656
  ],
  [
   144.97789001464844,
   -64.89473724365234
  ],
  [
   145.66319274902344,
   -65.9015121459961
  ],
  [
   146.3383331298828,
   -66.9109115600586
  ],
  [
   147.0033721923828,
   -67.92283630371094
  ],
  [
   147.6583251953125,
   -68.93719482421875
  ],
  [
   148.30325317382812,
   -69.95388793945312
  ],
  [
   148.93817138671875,
   -70.97281646728516
  ],
  [
   149.56317138671875,
   -71.993896484375
  ],
  [
   150.17825317382812,
   -73.01702880859375
  ],
  [
   150.78341674804688,
   -74.04212188720703
  ],
  [
   151.37875366210938,
   -75.06909942626953
  ],
  [
   151.9642791748047,
   -76.09786987304688
  ],
  [
   152.54005432128906,
   -77.12834930419922
  ],
  [
   153.10609436035156,
   -78.16043853759766
  ],
  [
   153.66246032714844,
   -79.19406127929688
  ],
  [
   154.20919799804688,
   -80.22913360595703
  ],
  [
   154.74632263183594,
   -81.26558685302734
  ],
  [
   155.27389526367188,
   -82.30330657958984
  ],
  [
   155.79196166992188,
   -83.34223937988281
  ],
  [
   156.30056762695312,
   -84.3823013305664
  ],
  [
   156.7997589111328,
   -85.42340087890625
  ],
  [
   157.28955078125,
   -86.46546173095703
  ],
  [
   157.77000427246094,
   -87.50843048095703
  ],
  [
   158.2411651611328,
   -88.55220794677734
  ],
  [
   158.7030792236328,
   -89.59673309326172
  ],
  [
   159.1558074951172,
   -90.64191436767578
  ],
  [
   159.59938049316406,
   -91.68769836425781
  ],
  [
   160.03379821777344,
   -92.73400115966797
  ],
  [
   160.4591522216797,
   -93.78075408935547
  ],
  [
   160.87547302246094,
   -94.82788848876953
  ],
  [
   161.28282165527344,
   -95.87533569335938
  ],
  [
   161.6812286376953,
   -96.92302703857422
  ],
  [
   162.07073974609375,
   -97.97087860107422
  ],
  [
   162.45140075683594,
   -99.01884460449219
  ],
  [
   162.82325744628906,
   -100.06685638427734
  ],
  [
   163.1863555908203,
   -101.1148452758789
  ],
  [
   163.54075622558594,
   -102.1627426147461
  ],
  [
   163.886474609375,
   -103.21048736572266
  ],
  [
   164.22360229492188,
   -104.25801849365234
  ],
  [
   164.55213928222656,
   -105.3052749633789
  ],
  [
   164.8721466064453,
   -106.35218811035156
  ],
  [
   165.1836700439453,
   -107.3987045288086
  ],
  [
   165.48678588867188,
   -108.44477844238281
  ],
  [
   165.78150939941406,
   -109.4903335571289
  ],
  [
   166.06787109375,
   -110.53531646728516
  ],
  [
   166.34593200683594,
   -111.57966613769531
  ],
  [
   166.6157684326172,
   -112.62332153320312
  ],
  [
   166.8773956298828,
   -113.66625213623047
  ],
  [
   167.13087463378906,
   -114.7083740234375
  ],
  [
   167.37623596191406,
   -115.74964141845703
  ],
  [
   167.613525390625,
   -116.7900161743164
  ],
  [
   167.84278869628906,
   -117.82942962646484
  ],
  [
   168.06411743164062,
   -118.86783599853516
  ],
  [
   168.2775115966797,
   -119.90518188476562
  ],
  [
   168.4830322265625,
   -120.94140625
  ],
  [
   168.68072509765625,
   -121.97647857666016
  ],
  [
   168.8706512451172,
   -123.01034545898438
  ],
  [
   169.05284118652344,
   -124.04296112060547
  ],
  [
   169.22732543945312,
   -125.07426452636719
  ],
  [
   169.39418029785156,
   -126.10421752929688
  ],
  [
   169.55345153808594,
   -127.13277435302734
  ],
  [
   169.70516967773438,
   -128.15988159179688
  ],
  [
   169.84939575195312,
   -129.1855010986328
  ],
  [
   169.98617553710938,
   -130.2095947265625
  ],
  [
   170.11553955078125,
   -131.2321014404297
  ],
  [
   170.237548828125,
   -132.25299072265625
  ],
  [
   170.35223388671875,
   -133.272216796875
  ],
  [
   170.45965576171875,
   -134.28973388671875
  ],
  [
   170.5598602294922,
   -135.30551147460938
  ],
  [
   170.65289306640625,
   -136.3195037841797
  ],
  [
   170.73880004882812,
   -137.33168029785156
  ],
  [
   170.817626953125,
   -138.3419647216797
  ],
  [
   170.88941955566406,
   -139.350341796875
  ],
  [
   170.9542236328125,
   -140.35679626464844
  ],
  [
   171.01210021972656,
   -141.36126708984375
  ],
  [
   171.0630645751953,
   -142.3637237548828
  ],
  [
   171.107177734375,
   -143.36412048339844
  ],
  [
   171.14450073242188,
   -144.36244201660156
  ],
  [
   171.17506408691406,
   -145.35862731933594
  ],
  [
   171.1989288330078,
   -146.35264587402344
  ],
  [
   171.2161102294922,
   -147.34446716308594
  ],
  [
   171.22666931152344,
   -148.33407592773438
  ],
  [
   171.2306671142578,
   -149.32139587402344
  ],
  [
   171.2281494140625,
   -150.30642700195312
  ],
  [
   171.21914672851562,
   -151.28915405273438
  ],
  [
   171.2036895751953,
   -152.26951599121094
  ],
  [
   171.1818389892578,
   -153.2474822998047
  ],
  [
   171.1536407470703,
   -154.2230224609375
  ],
  [
   171.119140625,
   -155.1961212158203
  ],
  [
   171.078369140625,
   -156.166748046875
  ],
  [
   171.03138732910156,
   -157.13485717773438
  ],
  [
   170.9782257080078,
   -158.10043334960938
  ],
  [
   170.9189453125,
   -159.06344604492188
  ],
  [
   170.85357666015625,
   -160.0238494873047
  ],
  [
   170.7821807861328,
   -160.9816436767578
  ],
  [
   170.7047882080078,
   -161.936767578125
  ]
 ],
 "velocities": [
  [
   18.287578582763672,
   0.050109539180994034
  ],
  [
   18.255022048950195,
   0.07216321676969528
  ],
  [
   18.16414451599121,
   0.07801838219165802
  ],
  [
   18.07254409790039,
   0.0832865908741951
  ],
  [
   17.960002899169922,
   0.08936016261577606
  ],
  [
   17.84203338623047,
   0.09569048881530762
  ],
  [
   17.726566314697266,
   0.10143198817968369
  ],
  [
   17.616670608520508,
   0.09880419075489044
  ],
  [
   17.510217666625977,
   0.07566781342029572
  ],
  [
   17.400259017944336,
   0.0651903972029686
  ],
  [
   17.29093360900879,
   0.06094326078891754
  ],
  [
   17.22001075744629,
   -0.09620656818151474
  ],
  [
   17.147871017456055,
   -0.2734924852848053
  ],
  [
   17.07408905029297,
   -0.460853636264801
  ],
  [
   16.99867057800293,
   -0.6500664949417114
  ],
  [
   16.92171859741211,
   -0.8378888368606567
  ],
  [
   16.84331703186035,
   -1.0231400728225708
  ],
  [
   16.763517379760742,
   -1.2058675289154053
  ],
  [
   16.68235206604004,
   -1.3861957788467407
  ],
  [
   16.599849700927734,
   -1.564211130142212
  ],
  [
   16.516056060791016,
   -1.7400037050247192
  ],
  [
   16.431015014648438,
   -1.9134981632232666
  ],
  [
   16.34477424621582,
   -2.0846827030181885
  ],
  [
   16.257356643676758,
   -2.253614664077759
  ],
  [
   16.168807983398438,
   -2.420321464538574
  ],
  [
   16.07914924621582,
   -2.5848045349121094
  ],
  [
   15.988434791564941,
   -2.7470524311065674
  ],
  [
   15.89669418334961,
   -2.907085657119751
  ],
  [
   15.803966522216797,
   -3.0649311542510986
  ],
  [
   15.71027946472168,
   -3.220611333847046
  ],
  [
   15.615662574768066,
   -3.374145746231079
  ],
  [
   15.520149230957031,
   -3.5255379676818848
  ],
  [
   15.42378044128418,
   -3.674795389175415
  ],
  [
   15.326583862304688,
   -3.8219406604766846
  ],
  [
   15.228590965270996,
   -3.966984272003174
  ],
  [
   15.129830360412598,
   -4.109940052032471
  ],
  [
   15.030332565307617,
   -4.250819206237793
  ],
  [
   14.930130004882812,
   -4.389648914337158
  ],
  [
   14.829240798950195,
   -4.526446342468262
  ],
  [
   14.727705955505371,
   -4.661218166351318
  ],
  [
   14.625543594360352,
   -4.793984889984131
  ],
  [
   14.522781372070312,
   -4.924756050109863
  ],
  [
   14.41945743560791,
   -5.053543567657471
  ],
  [
   14.315579414367676,
   -5.180372714996338
  ],
  [
   14.211182594299316,
   -5.3052544593811035
  ],
  [
   14.106285095214844,
   -5.428210735321045
  ],
  [
   14.000920295715332,
   -5.549250602722168
  ],
  [
   13.895110130310059,
   -5.668392658233643
  ],
  [
   13.788875579833984,
   -5.78564977645874
  ],
  [
   13.682236671447754,
   -5.9010419845581055
  ],
  [
   13.57521915435791,
   -6.014581680297852
  ],
  [
   13.467841148376465,
   -6.126287937164307
  ],
  [
   13.360130310058594,
   -6.236172199249268
  ],
  [
   13.252105712890625,
   -6.344244480133057
  ],
  [
   13.143783569335938,
   -6.450538635253906
  ],
  [
   13.035181999206543,
   -6.555060386657715
  ],
  [
   12.926328659057617,
   -6.6578240394592285
  ],
  [
   12.817239761352539,
   -6.758841037750244
  ],
  [
   12.707932472229004,
   -6.8581342697143555
  ],
  [
   12.598424911499023,
   -6.955709934234619
  ],
  [
   12.488739013671875,
   -7.051587104797363
  ],
  [
   12.378890991210938,
   -7.145785331726074
  ],
  [
   12.26889419555664,
   -7.23832368850708
  ],
  [
   12.158770561218262,
   -7.329212188720703
  ],
  [
   12.04853343963623,
   -7.418469429016113
  ],
  [
   11.93819808959961,
   -7.506105422973633
  ],
  [
   11.827787399291992,
   -7.592134475708008
  ],
  [
   11.717313766479492,
   -7.676575660705566
  ],
  [
   11.60678768157959,
   -7.759444236755371
  ],
  [
   11.496223449707031,
   -7.840752124786377
  ],
  [
   11.385641098022461,
   -7.920515537261963
  ],
  [
   11.275053977966309,
   -7.998750686645508
  ],
  [
   11.164469718933105,
   -8.075468063354492
  ],
  [
   11.053912162780762,
   -8.150686264038086
  ],
  [
   10.943388938903809,
   -8.224421501159668
  ],
  [
   10.832911491394043,
   -8.296683311462402
  ],
  [
   10.722495079040527,
   -8.3674898147583
  ],
  [
   10.612153053283691,
   -8.436853408813477
  ],
  [
   10.501895904541016,
   -8.504789352416992
  ],
  [
   10.391731262207031,
   -8.571311950683594
  ],
  [
   10.281673431396484,
   -8.636436462402344
  ],
  [
   10.171733856201172,
   -8.700180053710938
  ],
  [
   10.061931610107422,
   -8.762547492980957
  ],
  [
   9.952264785766602,
   -8.823561668395996
  ],
  [
   9.842751502990723,
   -8.883234024047852
  ],
  [
   9.733397483825684,
   -8.941577911376953
  ],
  [
   9.624215126037598,
   -8.998605728149414
  ],
  [
   9.515218734741211,
   -9.054329872131348
  ],
  [
   9.406411170959473,
   -9.108763694763184
  ],
  [
   9.29780387878418,
   -9.1619234085083
  ],
  [
   9.189406394958496,
   -9.213820457458496
  ],
  [
   9.08122730255127,
   -9.264472961425781
  ],
  [
   8.973270416259766,
   -9.31389045715332
  ],
  [
   8.865550994873047,
   -9.36208438873291
  ],
  [
   8.758076667785645,
   -9.409070014953613
  ],
  [
   8.650851249694824,
   -9.45485782623291
  ],
  [
   8.5438871383667,
   -9.499468803405762
  ],
  [
   8.437190055847168,
   -9.5429105758667
  ],
  [
   8.330765724182129,
   -9.585190773010254
  ],
  [
   8.224623680114746,
   -9.626324653625488
  ],
  [
   8.118765830993652,
   -9.66633129119873
  ],
  [
   8.013205528259277,
   -9.705220222473145
  ],
  [
   7.907946586608887,
   -9.74299430847168
  ],
  [
   7.802995204925537,
   -9.779677391052246
  ],
  [
   7.698357582092285,
   -9.815282821655273
  ],
  [
   7.594043254852295,
   -9.849812507629395
  ],
  [
   7.490052223205566,
   -9.883284568786621
  ],
  [
   7.386390686035156,
   -9.9157075881958
  ],
  [
   7.2830705642700195,
   -9.947096824645996
  ],
  [
   7.180095672607422,
   -9.977455139160156
  ],
  [
   7.077463626861572,
   -10.006807327270508
  ],
  [
   6.975187301635742,
   -10.035163879394531
  ],
  [
   6.873269081115723,
   -10.062525749206543
  ],
  [
   6.771716117858887,
   -10.088912963867188
  ],
  [
   6.670533180236816,
   -10.114330291748047
  ],
  [
   6.569720268249512,
   -10.138794898986816
  ],
  [
   6.46928596496582,
   -10.162315368652344
  ],
  [
   6.369232177734375,
   -10.18490219116211
  ],
  [
   6.2695631980896,
   -10.206565856933594
  ],
  [
   6.170286178588867,
   -10.227315902709961
  ],
  [
   6.0714006423950195,
   -10.247166633605957
  ],
  [
   5.972912311553955,
   -10.266127586364746
  ],
  [
   5.874825477600098,
   -10.284204483032227
  ],
  [
   5.7771406173706055,
   -10.301414489746094
  ],
  [
   5.679863452911377,
   -10.317766189575195
  ],
  [
   5.5829997062683105,
   -10.333269119262695
  ],
  [
   5.486546993255615,
   -10.347935676574707
  ],
  [
   5.3905181884765625,
   -10.361770629882812
  ],
  [
   5.294908046722412,
   -10.374787330627441
  ],
  [
   5.199717044830322,
   -10.386996269226074
  ],
  [
   5.104953765869141,
   -10.398406982421875
  ],
  [
   5.010618209838867,
   -10.409027099609375
  ],
  [
   4.916713237762451,
   -10.418863296508789
  ],
  [
   4.823244094848633,
   -10.427933692932129
  ],
  [
   4.730207920074463,
   -10.43624210357666
  ],
  [
   4.637609481811523,
   -10.44379711151123
  ],
  [
   4.545454025268555,
   -10.450610160827637
  ],
  [
   4.453737258911133,
   -10.456695556640625
  ],
  [
   4.362465858459473,
   -10.46205997467041
  ],
  [
   4.271643161773682,
   -10.466700553894043
  ],
  [
   4.181263446807861,
   -10.470641136169434
  ],
  [
   4.091336727142334,
   -10.473886489868164
  ],
  [
   4.001859188079834,
   -10.476441383361816
  ],
  [
   3.9128329753875732,
   -10.478321075439453
  ],
  [
   3.824260711669922,
   -10.479528427124023
  ],
  [
   3.736145257949829,
   -10.48007583618164
  ],
  [
   3.6484858989715576,
   -10.47996997833252
  ],
  [
   3.5612847805023193,
   -10.479219436645508
  ],
  [
   3.474545478820801,
   -10.477831840515137
  ],
  [
   3.38826322555542,
   -10.475815773010254
  ],
  [
   3.302441358566284,
   -10.473182678222656
  ],
  [
   3.2170815467834473,
   -10.469935417175293
  ],
  [
   3.132185459136963,
   -10.466087341308594
  ],
  [
   3.0477540493011475,
   -10.461638450622559
  ],
  [
   2.963787078857422,
   -10.456602096557617
  ],
  [
   2.8802847862243652,
   -10.45098876953125
  ],
  [
   2.7972476482391357,
   -10.444799423217773
  ],
  [
   2.714674711227417,
   -10.438047409057617
  ],
  [
   2.6325721740722656,
   -10.430743217468262
  ],
  [
   2.5509350299835205,
   -10.422884941101074
  ],
  [
   2.469766855239868,
   -10.414483070373535
  ],
  [
   2.389065980911255,
   -10.405550003051758
  ],
  [
   2.308833122253418,
   -10.396089553833008
  ],
  [
   2.2290685176849365,
   -10.3861083984375
  ],
  [
   2.1497726440429688,
   -10.375615119934082
  ],
  [
   2.0709469318389893,
   -10.364616394042969
  ],
  [
   1.9925892353057861,
   -10.353117942810059
  ],
  [
   1.9146982431411743,
   -10.341129302978516
  ],
  [
   1.8372756242752075,
   -10.328654289245605
  ],
  [
   1.7603238821029663,
   -10.315701484680176
  ],
  [
   1.6838401556015015,
   -10.302281379699707
  ],
  [
   1.6078213453292847,
   -10.28839111328125
  ],
  [
   1.5322719812393188,
   -10.274044036865234
  ],
  [
   1.457191824913025,
   -10.259243965148926
  ],
  [
   1.3825788497924805,
   -10.243997573852539
  ],
  [
   1.3084325790405273,
   -10.228316307067871
  ],
  [
   1.234752893447876,
   -10.212201118469238
  ],
  [
   1.1615386009216309,
   -10.195657730102539
  ],
  [
   1.088786005973816,
   -10.178696632385254
  ],
  [
   1.0165047645568848,
   -10.161321640014648
  ],
  [
   0.9446886777877808,
   -10.143540382385254
  ],
  [
   0.8733329176902771,
   -10.125353813171387
  ],
  [
   0.8024418950080872,
   -10.106776237487793
  ],
  [
   0.7320132851600647,
   -10.08780574798584
  ],
  [
   0.6620495319366455,
   -10.068452835083008
  ],
  [
   0.5925427675247192,
   -10.048720359802246
  ],
  [
   0.5235012769699097,
   -10.028621673583984
  ],
  [
   0.45491737127304077,
   -10.008148193359375
  ],
  [
   0.38679248094558716,
   -9.987322807312012
  ],
  [
   0.3191271126270294,
   -9.966134071350098
  ],
  [
   0.2519170641899109,
   -9.944597244262695
  ],
  [
   0.18516609072685242,
   -9.922718048095703
  ],
  [
   0.11886914819478989,
   -9.900493621826172
  ],
  [
   0.05302674323320389,
   -9.877941131591797
  ],
  [
   -0.012361124157905579,
   -9.855053901672363
  ],
  [
   -0.07729627192020416,
   -9.83184814453125
  ],
  [
   -0.14177998900413513,
   -9.808328628540039
  ],
  [
   -0.205813467502594,
   -9.784491539001465
  ],
  [
   -0.26939600706100464,
   -9.760350227355957
  ],
  [
   -0.3325308859348297,
   -9.735905647277832
  ],
  [
   -0.3952194154262543,
   -9.711165428161621
  ],
  [
   -0.4574587047100067,
   -9.686123847961426
  ],
  [
   -0.5192558169364929,
   -9.660799980163574
  ],
  [
   -0.5806068778038025,
   -9.635199546813965
  ],
  [
   -0.6415170431137085,
   -9.6093111038208
  ],
  [
   -0.7019861340522766,
   -9.583150863647461
  ],
  [
   -0.7620120048522949,
   -9.556721687316895
  ],
  [
   -0.8216008543968201,
   -9.530030250549316
  ]
 ],
 "headings": [
  [
   0.9999269077563389,
   0.01209045676747631
  ],
  [
   0.9999121067468355,
   0.01325815903905953
  ],
  [
   0.9999089829089202,
   0.013491697374640182
  ],
  [
   0.9999067015720208,
   0.013659727353126396
  ],
  [
   0.999904484040177,
   0.01382109967938809
  ],
  [
   0.9999028966034469,
   0.013935471432164389
  ],
  [
   0.9999021827381164,
   0.013986599141695998
  ],
  [
   0.9999044527509724,
   0.013823363150061245
  ],
  [
   0.9999093974338976,
   0.013460940657313469
  ],
  [
   0.9999152436651388,
   0.013019427256451208
  ],
  [
   0.9999220646584448,
   0.012484574850312301
  ],
  [
   0.99999506058244,
   0.0031430575435428486
  ],
  [
   0.9999698320209429,
   -0.007767563839924198
  ],
  [
   0.999819797701193,
   -0.018983469776241976
  ],
  [
   0.9995431865959641,
   -0.030222808102256127
  ],
  [
   0.999141442558763,
   -0.04142918972890953
  ],
  [
   0.9986160937137618,
   -0.052591799511590875
  ],
  [
   0.9979687363027687,
   -0.06370558344646791
  ],
  [
   0.9972009718308577,
   -0.07476778570743588
  ],
  [
   0.9963142685645304,
   -0.08577807560632644
  ],
  [
   0.995310112255496,
   -0.09673562137057859
  ],
  [
   0.9941899491089177,
   -0.10763988615196403
  ],
  [
   0.9929553130001443,
   -0.1184894357518231
  ],
  [
   0.9916075485208691,
   -0.12928445272511455
  ],
  [
   0.9901483770892928,
   -0.14002211020920813
  ],
  [
   0.9885788767772434,
   -0.15070436088528985
  ],
  [
   0.9869008158518965,
   -0.16132817382856962
  ],
  [
   0.985115479362269,
   -0.17189384026441193
  ],
  [
   0.9832243912677429,
   -0.18240009982501798
  ],
  [
   0.9812287048849806,
   -0.1928476826662525
  ],
  [
   0.9791298562807157,
   -0.20323563796663457
  ],
  [
   0.9769292845650381,
   -0.21356304211928342
  ],
  [
   0.9746285208751455,
   -0.22382860920071407
  ],
  [
   0.9722288655366138,
   -0.23403211962760362
  ],
  [
   0.9697316910338131,
   -0.24417298664000764
  ],
  [
   0.9671384282946356,
   -0.25425038941126904
  ],
  [
   0.9644504038520277,
   -0.26426391828938833
  ],
  [
   0.9616686005000554,
   -0.2742143373572299
  ],
  [
   0.9587949598216782,
   -0.2840989704672416
  ],
  [
   0.9558304459502108,
   -0.2939186258041859
  ],
  [
   0.9527762838356347,
   -0.3036731021351052
  ],
  [
   0.9496340949971631,
   -0.31336095101163924
  ],
  [
   0.9464050584308107,
   -0.3229821440522276
  ],
  [
   0.9430901497255665,
   -0.3325371700887115
  ],
  [
   0.9396910723232237,
   -0.3420243976619649
  ],
  [
   0.9362088203032749,
   -0.3514442271347622
  ],
  [
   0.9326447307566818,
   -0.360796072860829
  ],
  [
   0.9290002379787026,
   -0.3700791237499273
  ],
  [
   0.9252758753203156,
   -0.3792948121846959
  ],
  [
   0.9214739582002353,
   -0.38844014256869874
  ],
  [
   0.917594515308685,
   -0.39751767945013394
  ],
  [
   0.9136399426337383,
   -0.4065243599394991
  ],
  [
   0.909610798140578,
   -0.4154614252924821
  ],
  [
   0.9055081920521785,
   -0.42432878069534136
  ],
  [
   0.9013331602337723,
   -0.4331264645146967
  ],
  [
   0.8970870114308689,
   -0.4418539282636652
  ],
  [
   0.8927713562191455,
   -0.45051005040357045
  ],
  [
   0.8883871571362058,
   -0.45909504357534786
  ],
  [
   0.8839347277912236,
   -0.4676103046390823
  ],
  [
   0.879416846410846,
   -0.4760525288755459
  ],
  [
   0.8748332390465463,
   -0.4844241982594679
  ],
  [
   0.8701856862393215,
   -0.4927239302735368
  ],
  [
   0.8654745370587252,
   -0.5009529176509357
  ],
  [
   0.8607015036207296,
   -0.509109930825372
  ],
  [
   0.8558676402447029,
   -0.517194917204301
  ],
  [
   0.8509739884986056,
   -0.5252078359076292
  ],
  [
   0.8460215062073062,
   -0.5331487700770967
  ],
  [
   0.8410111342608368,
   -0.5410178112126259
  ],
  [
   0.8359441621170911,
   -0.548814502197559
  ],
  [
   0.8308215125522281,
   -0.5565389602538423
  ],
  [
   0.825644091455733,
   -0.564191309968735
  ],
  [
   0.8204133209033999,
   -0.5717709181868688
  ],
  [
   0.8151297858313548,
   -0.5792783719858094
  ],
  [
   0.8097946634265892,
   -0.5867133909208286
  ],
  [
   0.8044088135905569,
   -0.5940761404212701
  ],
  [
   0.7989734799678954,
   -0.6013662597020147
  ],
  [
   0.7934894226999604,
   -0.6085840419065255
  ],
  [
   0.7879576274490633,
   -0.6157294676599807
  ],
  [
   0.7823791539098994,
   -0.6228024241500911
  ],
  [
   0.7767544695243268,
   -0.6298035360919957
  ],
  [
   0.7710847736342603,
   -0.6367324963196095
  ],
  [
   0.7653714392185413,
   -0.6435888128522268
  ],
  [
   0.7596151555848073,
   -0.6503728280039603
  ],
  [
   0.7538160671052524,
   -0.6570854868082003
  ],
  [
   0.7479760448463268,
   -0.6637257237263339
  ],
  [
   0.7420953831831598,
   -0.6702942952601038
  ],
  [
   0.736175604718178,
   -0.6767905724947895
  ],
  [
   0.730216973504909,
   -0.6832153186260763
  ],
  [
   0.7242206388702014,
   -0.6895683187577843
  ],
  [
   0.7181873806835403,
   -0.6958497583723915
  ],
  [
   0.7121179664678426,
   -0.7020598278164792
  ],
  [
   0.7060133400970295,
   -0.7081985340319734
  ],
  [
   0.6998738690882804,
   -0.7142664540403676
  ],
  [
   0.6937012387314534,
   -0.7202628626983673
  ],
  [
   0.6874956068644914,
   -0.7261885364986318
  ],
  [
   0.6812580750766442,
   -0.7320433287332556
  ],
  [
   0.6749891559255596,
   -0.737827648833317
  ],
  [
   0.6686899379448908,
   -0.7435413686482131
  ],
  [
   0.6623607118440366,
   -0.7491850822096374
  ],
  [
   0.6560027495972897,
   -0.7547584994690657
  ],
  [
   0.6496165193401995,
   -0.7602620454819011
  ],
  [
   0.6432030834027925,
   -0.765695627192124
  ],
  [
   0.6367626826192778,
   -0.771059845941611
  ],
  [
   0.6302965686750502,
   -0.7763544522423103
  ],
  [
   0.6238051660590199,
   -0.7815798838238345
  ],
  [
   0.6172890917693582,
   -0.7867364089595452
  ],
  [
   0.6107495841442728,
   -0.791823809611455
  ],
  [
   0.6041870375493402,
   -0.7968425337903042
  ],
  [
   0.5976016161783145,
   -0.8017931830223218
  ],
  [
   0.5909947516744313,
   -0.8066754015669979
  ],
  [
   0.5843670209553272,
   -0.8114894853414899
  ],
  [
   0.5777187724668376,
   -0.8162358849863257
  ],
  [
   0.5710507759510686,
   -0.8209147405703485
  ],
  [
   0.564363795335604,
   -0.8255261997746604
  ],
  [
   0.5576588097465975,
   -0.8300702692615898
  ],
  [
   0.5509359081570758,
   -0.8345475571248999
  ],
  [
   0.5441958296694801,
   -0.838958222422515
  ],
  [
   0.5374393076035302,
   -0.8433024313036445
  ],
  [
   0.5306670694544202,
   -0.847580356896417
  ],
  [
   0.5238793831606655,
   -0.8517924582309946
  ],
  [
   0.5170774137251177,
   -0.855938635776738
  ],
  [
   0.5102609548923154,
   -0.8600196264692932
  ],
  [
   0.503431388066421,
   -0.8640352061747928
  ],
  [
   0.49658894589101016,
   -0.867985840217947
  ],
  [
   0.4897343111799697,
   -0.8718717247698085
  ],
  [
   0.48286792777363735,
   -0.8756931907509578
  ],
  [
   0.4759906981405991,
   -0.8794503142779728
  ],
  [
   0.46910258218245643,
   -0.883143684453301
  ],
  [
   0.46220423083750944,
   -0.8867735049018471
  ],
  [
   0.45529700080765023,
   -0.890339621187083
  ],
  [
   0.4483805880782481,
   -0.8938427424522752
  ],
  [
   0.4414558628549105,
   -0.8972829660430574
  ],
  [
   0.4345232136734321,
   -0.900660633523478
  ],
  [
   0.42758326061132734,
   -0.903975970501974
  ],
  [
   0.4206366181540512,
   -0.9072292077903593
  ],
  [
   0.4136836527145885,
   -0.9104206914809855
  ],
  [
   0.4067247217394572,
   -0.9135507652703057
  ],
  [
   0.3997604179640921,
   -0.9166196638896497
  ],
  [
   0.3927918184743605,
   -0.9196274176750088
  ],
  [
   0.3858185269661958,
   -0.9225746930463868
  ],
  [
   0.37884136146206926,
   -0.9254616268898272
  ],
  [
   0.3718608904492775,
   -0.9282884671018328
  ],
  [
   0.36487718106584616,
   -0.9310556603863389
  ],
  [
   0.3578912839334949,
   -0.9337632616913317
  ],
  [
   0.3509032525149764,
   -0.9364117189433346
  ],
  [
   0.34391387949301355,
   -0.9390011946169531
  ],
  [
   0.33692345345684965,
   -0.9415320422113684
  ],
  [
   0.32993225495877654,
   -0.9440046118202055
  ],
  [
   0.3229408087064998,
   -0.9464191640451877
  ],
  [
   0.31594938149791524,
   -0.948776047511258
  ],
  [
   0.30895873901098536,
   -0.9510754426378287
  ],
  [
   0.301969136384537,
   -0.9533177018555655
  ],
  [
   0.2949810756370738,
   -0.9555030952414518
  ],
  [
   0.2879947985809024,
   -0.9576319731453965
  ],
  [
   0.2810107952263851,
   -0.9597046071402568
  ],
  [
   0.2740295504898581,
   -0.9617212722292912
  ],
  [
   0.2670510309008691,
   -0.9636823890135084
  ],
  [
   0.260075965281577,
   -0.9655881587316903
  ],
  [
   0.2531048218520286,
   -0.9674388606807424
  ],
  [
   0.24613806381213574,
   -0.9692347773077548
  ],
  [
   0.2391756321664389,
   -0.9709763215330147
  ],
  [
   0.23221797737316957,
   -0.9726637707783271
  ],
  [
   0.2252660639810324,
   -0.9742972854414065
  ],
  [
   0.2183195555928179,
   -0.9758773343231999
  ],
  [
   0.211378886803796,
   -0.9774041979721532
  ],
  [
   0.2044447481321986,
   -0.9788781052619177
  ],
  [
   0.19751730470335627,
   -0.9802994003582383
  ],
  [
   0.19059671533357475,
   -0.9816684226886654
  ],
  [
   0.18368339445579138,
   -0.9829854579805329
  ],
  [
   0.17677801394432147,
   -0.9842507474144488
  ],
  [
   0.16988045495285317,
   -0.9854646777155494
  ],
  [
   0.16299111690985763,
   -0.9866275365144017
  ],
  [
   0.15611065770384108,
   -0.9877395722310989
  ],
  [
   0.1492389417653496,
   -0.9888011621457362
  ],
  [
   0.14237661751498362,
   -0.989812557399123
  ],
  [
   0.13552353832064779,
   -0.9907741269134211
  ],
  [
   0.12868034333844244,
   -0.9916861243550302
  ],
  [
   0.12184740389996039,
   -0.9925488452276996
  ],
  [
   0.11502482230275977,
   -0.9933626177052459
  ],
  [
   0.10821296030183074,
   -0.9941277358683412
  ],
  [
   0.10141217525603974,
   -0.9948444957428464
  ],
  [
   0.09462255501301337,
   -0.9955132204460216
  ],
  [
   0.08784471294861029,
   -0.9961341809249276
  ],
  [
   0.08107819699186156,
   -0.996707743509876
  ],
  [
   0.07432414249760295,
   -0.9972341359189406
  ],
  [
   0.06758235368072547,
   -0.9977136991496977
  ],
  [
   0.06085316112536605,
   -0.998146729083981
  ],
  [
   0.054136625293625756,
   -0.9985335376449894
  ],
  [
   0.047433334128625056,
   -0.9988744059257111
  ],
  [
   0.040743339590765745,
   -0.9991696453951109
  ],
  [
   0.03406695536405992,
   -0.9994195528166453
  ],
  [
   0.0274042248259225,
   -0.9996244337058244
  ],
  [
   0.02075571961900795,
   -0.9997845768479814
  ],
  [
   0.014121741218325292,
   -0.9999002832407653
  ],
  [
   0.007501788110059304,
   -0.9999718611916796
  ],
  [
   0.0008966862188663371,
   -0.9999995979768317
  ],
  [
   -0.005693008709747537,
   -0.9999837946946094
  ],
  [
   -0.012268076436919384,
   -0.9999247443185602
  ],
  [
   -0.01882770269732168,
   -0.9998227430955655
  ],
  [
   -0.02537134350155192,
   -0.9996780956532589
  ],
  [
   -0.03189952364563778,
   -0.9994910806961618
  ],
  [
   -0.03841170663563701,
   -0.9992619980732469
  ],
  [
   -0.044907626021856946,
   -0.9989911436669902
  ],
  [
   -0.05138701911930267,
   -0.9986788143672781
  ],
  [
   -0.05784989286682276,
   -0.998325292625253
  ],
  [
   -0.06429572599540147,
   -0.9979308891996099
  ],
  [
   -0.07072506396224432,
   -0.997495847273329
  ],
  [
   -0.07713686128892969,
   -0.9970205136457787
  ]
 ],
 "heading_theta": [
  0.01209075134895965,
  0.013258547486959316,
  0.013492106714559249,
  0.013660152179343577,
  0.013821539741401878,
  0.013935922510221133,
  0.013987055203150689,
  0.013823803428328674,
  0.013461347203969076,
  0.013019795095233988,
  0.01248489919029172,
  0.003143062718510947,
  -0.007767641951434534,
  -0.018984610146739023,
  -0.03022741100461701,
  -0.04144105024855982,
  -0.052616073656695406,
  -0.06374875280349901,
  -0.07483762295037089,
  -0.08588361620369245,
  -0.09688713203762767,
  -0.10784883624244834,
  -0.11876846250204576,
  -0.1296473423969644,
  -0.1404837448724976,
  -0.15128073256389651,
  -0.16203630810034486,
  -0.17275180306238802,
  -0.18342695113391638,
  -0.1940634833696384,
  -0.2046613997695541,
  -0.21522070033366347,
  -0.22574098558780342,
  -0.23622292132224665,
  -0.24666677385310098,
  -0.2570725431803673,
  -0.2674406287782096,
  -0.2777726285432811,
  -0.2880665451047646,
  -0.2983239763593133,
  -0.3085454549391464,
  -0.31873018189593694,
  -0.32887882301995663,
  -0.33899257673369565,
  -0.3490703777727191,
  -0.35911329140146186,
  -0.3691213176199257,
  -0.3790941901119993,
  -0.3890340394065568,
  -0.39893820234250743,
  -0.4088100078712129,
  -0.4186466596735299,
  -0.42845002196222026,
  -0.43822049421144804,
  -0.44795860905343243,
  -0.4576642333301173,
  -0.4673365680931756,
  -0.4769762791328809,
  -0.48658536382005124,
  -0.49616049320332145,
  -0.5057048630760015,
  -0.5152172750156012,
  -0.5246994600768282,
  -0.5341503529952476,
  -0.5435702200869663,
  -0.5529593276680949,
  -0.5623180752127972,
  -0.5716468621952355,
  -0.580945422299302,
  -0.5902141549991597,
  -0.5994534597689718,
  -0.6086628039765198,
  -0.6178431197281871,
  -0.6269942738659164,
  -0.6361166658638737,
  -0.6452100294059502,
  -0.6542748971243615,
  -0.6633114021771638,
  -0.672319544564357,
  -0.6813002563923218,
  -0.6902532713449503,
  -0.6991780567900232,
  -0.7080751453597607,
  -0.7169458686347054,
  -0.7257888950343139,
  -0.7346052898230209,
  -0.7433942540525003,
  -0.7521568529871878,
  -0.7608928203109748,
  -0.76960242233997,
  -0.7782859253902821,
  -0.7869433294619119,
  -0.7955754335031866,
  -0.8041811722496686,
  -0.8127616109657945,
  -0.8213164833354565,
  -0.8298463219908712,
  -0.8383508606159298,
  -0.8468308981589603,
  -0.8552859019877435,
  -0.8637164047344985,
  -0.8721221400831158,
  -0.8805039069819216,
  -0.8888611727987001,
  -0.8971944701656671,
  -0.9055040653989312,
  -0.9137894258662769,
  -0.9220510841999214,
  -0.9302898393481911,
  -0.9385048923627579,
  -0.9466965095597324,
  -0.954865223571332,
  -0.9630110343975584,
  -0.9711339420384082,
  -0.9792336801777761,
  -0.9873110477639857,
  -0.9953660447970396,
  -1.003398671276937,
  -1.0114089272036768,
  -1.0193973452094784,
  -1.0273633926621235,
  -1.0353081348260478,
  -1.0432307727529242,
  -1.051131839074971,
  -1.0590113337921894,
  -1.066869523220686,
  -1.074706141044353,
  -1.0825219862115176,
  -1.0903170587221798,
  -1.0980905596280124,
  -1.1058435541934504,
  -1.1135757761023868,
  -1.1212874916709286,
  -1.1289787008990775,
  -1.1366494037868335,
  -1.1442998666503037,
  -1.1519303558055984,
  -1.1595408712527178,
  -1.1671308803594442,
  -1.1747014483902127,
  -1.1822523090289145,
  -1.1897834622755497,
  -1.1972954407623355,
  -1.2047877118570556,
  -1.2122608081919264,
  -1.2197144634508401,
  -1.2271489439499064,
  -1.2345645160052312,
  -1.2419611796168173,
  -1.2493392011007733,
  -1.2566983141409889,
  -1.2640387850535744,
  -1.2713606138385298,
  -1.278664066811963,
  -1.2859491439738742,
  -1.293215845324264,
  -1.3004647034953507,
  -1.3076954521710258,
  -1.3149080913512865,
  -1.3221026210361364,
  -1.3292795738577912,
  -1.3364389498162508,
  -1.3435802162792978,
  -1.3507041721952593,
  -1.3578108175641361,
  -1.3648998860698187,
  -1.3719716440284149,
  -1.3790263577560342,
  -1.3860640272526776,
  -1.3930843862022364,
  -1.4000879672369262,
  -1.4070747703567488,
  -1.4140445292455954,
  -1.4209977765356836,
  -1.4279342459109046,
  -1.4348544700034749,
  -1.4417581824972867,
  -1.448645383392341,
  -1.4555163390047454,
  -1.4623710493345001,
  -1.469209514381606,
  -1.4760320004621708,
  -1.4828382412600867,
  -1.4896290357236799,
  -1.4964035849046233,
  -1.5031624214351353,
  -1.509905545315216,
  -1.5166332228609747,
  -1.5233451877563002,
  -1.5300417063173049,
  -1.5367227785439868,
  -1.5433886707524547,
  -1.5500391166266008,
  -1.556674116166425,
  -1.5632944683202528,
  -1.5698996404558674,
  -1.5764893662571584,
  -1.5830647109885643,
  -1.5896251420178658,
  -1.5961703930289541,
  -1.6027012629701556,
  -1.6092174855253605,
  -1.6157190606945715,
  -1.622205988477786,
  -1.6286785351911153,
  -1.635136434518448,
  -1.641580485408113,
  -1.6480098889117816
 ],
 "steering_signals": [
  null,
  null,
  null,
  null,
  null,
  null,
  null,
  null,
  null,
  null,
  null,
  -0.02428800313899879,
  -0.02428800313899879,
  -0.02428800313899879,
  -0.02428800313899879,
  -0.02428800313899879,
  -0.02428800313899879,
  -0.02428800313899879,
  -0.02428800313899879,
  -0.02428800313899879,
  -0.02428800313899879,
  -0.02428800313899879,
  -0.02428800313899879,
  -0.02428800313899879,
  -0.02428800313899879,
  -0.02428800313899879,
  -0.02428800313899879,
  -0.02428800313899879,
  -0.02428800313899879,
  -0.02428800313899879,
  -0.02428800313899879,
  -0.02428800313899879,
  -0.02428800313899879,
  -0.02428800313899879,
  -0.02428800313899879,
  -0.02428800313899879,
  -0.02428800313899879,
  -0.02428800313899879,
  -0.02428800313899879,
  -0.02428800313899879,
  -0.02428800313899879,
  -0.02428800313899879,
  -0.02428800313899879,
  -0.02428800313899879,
  -0.02428800313899879,
  -0.02428800313899879,
  -0.02428800313899879,
  -0.02428800313899879,
  -0.02428800313899879,
  -0.02428800313899879,
  -0.02428800313899879,
  -0.02428800313899879,
  -0.02428800313899879,
  -0.02428800313899879,
  -0.02428800313899879,
  -0.02428800313899879,
  -0.02428800313899879,
  -0.02428800313899879,
  -0.02428800313899879,
  -0.02428800313899879,
  -0.02428800313899879,
  -0.02428800313899879,
  -0.02428800313899879,
  -0.02428800313899879,
  -0.02428800313899879,
  -0.02428800313899879,
  -0.02428800313899879,
  -0.02428800313899879,
  -0.02428800313899879,
  -0.02428800313899879,
  -0.02428800313899879,
  -0.02428800313899879,
  -0.02428800313899879,
  -0.02428800313899879,
  -0.02428800313899879,
  -0.02428800313899879,
  -0.02428800313899879,
  -0.02428800313899879,
  -0.02428800313899879,
  -0.02428800313899879,
  -0.02428800313899879,
  -0.02428800313899879,
  -0.02428800313899879,
  -0.02428800313899879,
  -0.02428800313899879,
  -0.02428800313899879,
  -0.02428800313899879,
  -0.02428800313899879,
  -0.02428800313899879,
  -0.02428800313899879,
  -0.02428800313899879,
  -0.02428800313899879,
  -0.02428800313899879,
  -0.02428800313899879,
  -0.02428800313899879,
  -0.02428800313899879,
  -0.02428800313899879,
  -0.02428800313899879,
  -0.02428800313899879,
  -0.02428800313899879,
  -0.02428800313899879,
  -0.02428800313899879,
  -0.02428800313899879,
  -0.02428800313899879,
  -0.02428800313899879,
  -0.02428800313899879,
  -0.02428800313899879,
  -0.02428800313899879,
  -0.02428800313899879,
  -0.02428800313899879,
  -0.02428800313899879,
  -0.02428800313899879,
  -0.02428800313899879,
  -0.02428800313899879,
  -0.02428800313899879,
  -0.02428800313899879,
  -0.02428800313899879,
  -0.02428800313899879,
  -0.02428800313899879,
  -0.02428800313899879,
  -0.02428800313899879,
  -0.02428800313899879,
  -0.02428800313899879,
  -0.02428800313899879,
  -0.02428800313899879,
  -0.02428800313899879,
  -0.02428800313899879,
  -0.02428800313899879,
  -0.02428800313899879,
  -0.02428800313899879,
  -0.02428800313899879,
  -0.02428800313899879,
  -0.02428800313899879,
  -0.02428800313899879,
  -0.02428800313899879,
  -0.02428800313899879,
  -0.02428800313899879,
  -0.02428800313899879,
  -0.02428800313899879,
  -0.02428800313899879,
  -0.02428800313899879,
  -0.02428800313899879,
  -0.02428800313899879,
  -0.02428800313899879,
  -0.02428800313899879,
  -0.02428800313899879,
  -0.02428800313899879,
  -0.02428800313899879,
  -0.02428800313899879,
  -0.02428800313899879,
  -0.02428800313899879,
  -0.02428800313899879,
  -0.02428800313899879,
  -0.02428800313899879,
  -0.02428800313899879,
  -0.02428800313899879,
  -0.02428800313899879,
  -0.02428800313899879,
  -0.02428800313899879,
  -0.02428800313899879,
  -0.02428800313899879,
  -0.02428800313899879,
  -0.02428800313899879,
  -0.02428800313899879,
  -0.02428800313899879,
  -0.02428800313899879,
  -0.02428800313899879,
  -0.02428800313899879,
  -0.02428800313899879,
  -0.02428800313899879,
  -0.02428800313899879,
  -0.02428800313899879,
  -0.02428800313899879,
  -0.02428800313899879,
  -0.02428800313899879,
  -0.02428800313899879,
  -0.02428800313899879,
  -0.02428800313899879,
  -0.02428800313899879,
  -0.02428800313899879,
  -0.02428800313899879,
  -0.02428800313899879,
  -0.02428800313899879,
  -0.02428800313899879,
  -0.02428800313899879,
  -0.02428800313899879,
  -0.02428800313899879,
  -0.02428800313899879,
  -0.02428800313899879,
  -0.02428800313899879,
  -0.02428800313899879,
  -0.02428800313899879,
  -0.02428800313899879,
  -0.02428800313899879,
  -0.02428800313899879,
  -0.02428800313899879,
  -0.02428800313899879,
  -0.02428800313899879,
  -0.02428800313899879,
  -0.02428800313899879,
  -0.02428800313899879,
  -0.02428800313899879,
  -0.02428800313899879,
  -0.02428800313899879,
  -0.02428800313899879,
  -0.02428800313899879,
  -0.02428800313899879,
  -0.02428800313899879
 ],
 "accelerations": [
  null,
  null,
  null,
  null,
  null,
  null,
  null,
  null,
  null,
  null,
  null,
  -0.040362313385545016,
  -0.04003263353569418,
  -0.03970677760706024,
  -0.03938448190113803,
  -0.039065947362086614,
  -0.038751293429046714,
  -0.03844045947299027,
  -0.03813340024424245,
  -0.037830025241001396,
  -0.037530238484661936,
  -0.037234042294053346,
  -0.03694136350035527,
  -0.03665216886282313,
  -0.03636635725266936,
  -0.036083921525421545,
  -0.035804734420380985,
  -0.03552880645935532,
  -0.03525606445186431,
  -0.034986486710112515,
  -0.03472000446015357,
  -0.03445655991738589,
  -0.034196100765220255,
  -0.03393861177418812,
  -0.033684039445562565,
  -0.033432337845250286,
  -0.03318345548543206,
  -0.03293734872796201,
  -0.03269400293976886,
  -0.03245333838720659,
  -0.032215357463330506,
  -0.031979990235050715,
  -0.03174719412609623,
  -0.031516972469215254,
  -0.03128923018377172,
  -0.031063963806985354,
  -0.030841121381562246,
  -0.030620693436136086,
  -0.030402642716283904,
  -0.030186922467417176,
  -0.02997349607299867,
  -0.029762338663505764,
  -0.02955341012673788,
  -0.02934669495605883,
  -0.029142145419659163,
  -0.028939746852330566,
  -0.028739446167397605,
  -0.028541240128220693,
  -0.028345081581932392,
  -0.02815094970632198,
  -0.027958798476885063,
  -0.027768620184500846,
  -0.027580390674218306,
  -0.02739407777118443,
  -0.027209662137131396,
  -0.02702711430656268,
  -0.026846395953387392,
  -0.026667503189111406,
  -0.026490409529850035,
  -0.026315076845058825,
  -0.026141473910871346,
  -0.025969597594513137,
  -0.025799425391677386,
  -0.025630906753876404,
  -0.02546405919142896,
  -0.025298847517076055,
  -0.025135234922395236,
  -0.024973216180217857,
  -0.024812768862197007,
  -0.024653870035038102,
  -0.024496488069551414,
  -0.024340613848064605,
  -0.024186235852131147,
  -0.024033335349585485,
  -0.0238818800090696,
  -0.02373186652320972,
  -0.023583263686654726,
  -0.023436056948796136,
  -0.023290237395450934,
  -0.023145769867165246,
  -0.02300264966408038,
  -0.022860856437387948,
  -0.022720385057434924,
  -0.022581198550508552,
  -0.022443293503500873,
  -0.022306658237789916,
  -0.02217126112091427,
  -0.022037118522303677,
  -0.0219041979701591,
  -0.021772467860338176,
  -0.021641925737227778,
  -0.021512563098711905,
  -0.021384372924651604,
  -0.021257310237062038,
  -0.021131391245555162,
  -0.021006605654663245,
  -0.020882920417922713,
  -0.02076032648348492,
  -0.020638803286082346,
  -0.02051836003120755,
  -0.02039895696443615,
  -0.020280602377079543,
  -0.020163296517192706,
  -0.020046994062506915,
  -0.01993171103640323,
  -0.019817418171493677,
  -0.019704112164913887,
  -0.019591782464040933,
  -0.019480412408952475,
  -0.019369990253712874,
  -0.0192605069834337,
  -0.01915195451994386,
  -0.01904432270863933,
  -0.018937588892545713,
  -0.01883175671732724,
  -0.01872681497817202,
  -0.018622755415525515,
  -0.018519566041223533,
  -0.018417236885090824,
  -0.01831575555616411,
  -0.018215111093834075,
  -0.018115301797705104,
  -0.01801630890069812,
  -0.017918115496253082,
  -0.017820740434861974,
  -0.017724152188566187,
  -0.01762834317464679,
  -0.017533314678972234,
  -0.01743906476731694,
  -0.0173455839827764,
  -0.017252832031165847,
  -0.017160834124897436,
  -0.017069580146363388,
  -0.01697904463773173,
  -0.01688923905119267,
  -0.016800140616172556,
  -0.01671175407428361,
  -0.0166240647137356,
  -0.01653706655404287,
  -0.016450752558938433,
  -0.016365110912419722,
  -0.016280146035655946,
  -0.01619583677799428,
  -0.01611219194815442,
  -0.01602918231523775,
  -0.015946815769362275,
  -0.015865092905934217,
  -0.01578398796857201,
  -0.01570350948770413,
  -0.01562366344326206,
  -0.015544413003054851,
  -0.015465762802215685,
  -0.015387719462166312,
  -0.015310267433693585,
  -0.015233399206284795,
  -0.015157113057640826,
  -0.01508140271567128,
  -0.01500625750478293,
  -0.014931678324133188,
  -0.01485765195475151,
  -0.014784179034276205,
  -0.014711263104976662,
  -0.014638870959076043,
  -0.014567018169951512,
  -0.014495691791390135,
  -0.014424886426813681,
  -0.0143546107893289,
  -0.014284844962912204,
  -0.014215582143562139,
  -0.01414682821362627,
  -0.014078574820106571,
  -0.014010819505247803,
  -0.013943542530648475,
  -0.01387676325278413,
  -0.013810455214930841,
  -0.01374462703012886,
  -0.01367926485311475,
  -0.013614386344947122,
  -0.013549947310115345,
  -0.013485990412904053,
  -0.013422465509688753,
  -0.013359394335306678,
  -0.013296773692326503,
  -0.013234577017078789,
  -0.013172831932683277,
  -0.013111502427304845,
  -0.013050613707854672,
  -0.012990160626847215,
  -0.012930115571126551,
  -0.01287049645385117,
  -0.012811288800977596,
  -0.012752495868525933,
  -0.012694085594715878,
  -0.012636092186120369,
  -0.012578513578219408,
  -0.012521304540893577,
  -0.012464491276056878,
  -0.012408064880090231
 ],
 "termination": "time_or_terminate"
}